unicms_template_unical/__init__.py
unicms_template_unical/apps.py
unicms_template_unical/settings.py
unicms_template_unical/locale/it/LC_MESSAGES/django.mo
unicms_template_unical/locale/it/LC_MESSAGES/django.po
unicms_template_unical/static/css/unicms_atlante.css
unicms_template_unical/static/css/unicms_exbriner.css
unicms_template_unical/static/css/unicms_ispa.css
unicms_template_unical/static/css/unicms_master_enetra.css
unicms_template_unical/static/css/unicms_master_mimi.css
unicms_template_unical/static/css/unicms_sba.css
unicms_template_unical/static/css/unicms_sssap.css
unicms_template_unical/static/css/unicms_star.css
unicms_template_unical/static/css/unicms_unical.css
unicms_template_unical/static/css/colors/unicms_atlante.css
unicms_template_unical/static/css/colors/unicms_exbriner.css
unicms_template_unical/static/css/colors/unicms_ispa.css
unicms_template_unical/static/css/colors/unicms_master_enetra.css
unicms_template_unical/static/css/colors/unicms_master_mimi.css
unicms_template_unical/static/css/colors/unicms_sba.css
unicms_template_unical/static/css/colors/unicms_sssap.css
unicms_template_unical/static/css/colors/unicms_star.css
unicms_template_unical/static/css/colors/unicms_unical.css
unicms_template_unical/static/fonts/TitilliumWeb-Black.ttf
unicms_template_unical/static/images/addressbook.svg
unicms_template_unical/static/images/agenda.jpg
unicms_template_unical/static/images/alert-red.svg
unicms_template_unical/static/images/banner_1.jpg
unicms_template_unical/static/images/chi.png
unicms_template_unical/static/images/dimes.svg
unicms_template_unical/static/images/en.png
unicms_template_unical/static/images/esp.png
unicms_template_unical/static/images/ita.png
unicms_template_unical/static/images/library1.jpg
unicms_template_unical/static/images/logo.png
unicms_template_unical/static/images/logo.svg
unicms_template_unical/static/images/logo1.svg
unicms_template_unical/static/images/logo_back.svg
unicms_template_unical-1.8.18.dist-info/licenses/AUTHORS
unicms_template_unical-1.8.18.dist-info/licenses/LICENSE
unicms_template_unical-1.8.18.dist-info/METADATA
unicms_template_unical-1.8.18.dist-info/WHEEL
unicms_template_unical-1.8.18.dist-info/top_level.txt
unicms_template_unical-1.8.18.dist-info/RECORD
