Metadata-Version: 2.4
Name: unicms_template_unical
Version: 1.8.18
Summary: uniCMS Unical Template based on Bootstrap Italia
Home-page: https://github.com/UniversitaDellaCalabria/unicms-template-unical
Author: Giuseppe De Marco, Francesco Filicetti
Author-email: giuseppe.demarco@unical.it, francesco.filicetti@unical.it
License: Apache License 2.0
Classifier: Environment :: Web Environment
Classifier: Framework :: Django
Classifier: Framework :: Django :: 2.0
Classifier: Framework :: Django :: 3.0
Classifier: Framework :: Django :: 4.0
Classifier: Intended Audience :: Developers
Classifier: License :: OSI Approved :: Apache Software License
Classifier: Operating System :: OS Independent
Classifier: Programming Language :: Python
Classifier: Programming Language :: Python :: 3
License-File: LICENSE
License-File: AUTHORS
Requires-Dist: unicms-template-italia
Dynamic: author
Dynamic: author-email
Dynamic: classifier
Dynamic: description
Dynamic: description-content-type
Dynamic: home-page
Dynamic: license
Dynamic: license-file
Dynamic: requires-dist
Dynamic: summary
